MANIFEST.in
README.txt
setup.cfg
setup.py
wiki2sphinx/Wiki2Sphinx.py
wiki2sphinx/__init__.py
wiki2sphinx.egg-info/PKG-INFO
wiki2sphinx.egg-info/SOURCES.txt
wiki2sphinx.egg-info/dependency_links.txt
wiki2sphinx.egg-info/entry_points.txt
wiki2sphinx.egg-info/namespace_packages.txt
wiki2sphinx.egg-info/not-zip-safe
wiki2sphinx.egg-info/requires.txt
wiki2sphinx.egg-info/top_level.txt
wiki2sphinx/placeholders/__init__.py
wiki2sphinx/placeholders/dummy.pdf
wiki2sphinx/placeholders/dummy.png
wiki2sphinx/placeholders/dummy.svg
wiki2sphinx/sphinx/Makefile
wiki2sphinx/sphinx/make.bat
wiki2sphinx/sphinx/source/conf.py