Metadata-Version: 1.0
Name: wiki2sphinx
Version: 0.2
Summary: tool for creating a sphinx document structure from a ReST-moin-wiki
Home-page: https://utils.icg.kfa-juelich.de/hg/wiki2sphinx/0.2/
Author: Henning Fleddermann
Author-email: zhick666@googlemail.com
License: GPL
Keywords: python,MoinMoin
Platform: any
Classifier: D
Classifier: e
Classifier: v
Classifier: e
Classifier: l
Classifier: o
Classifier: p
Classifier: m
Classifier: e
Classifier: n
Classifier: t
Classifier:  
Classifier: S
Classifier: t
Classifier: a
Classifier: t
Classifier: u
Classifier: s
Classifier:  
Classifier: :
Classifier: :
Classifier:  
Classifier: 5
Classifier:  
Classifier: -
Classifier:  
Classifier: P
Classifier: r
Classifier: o
Classifier: d
Classifier: u
Classifier: c
Classifier: t
Classifier: i
Classifier: o
Classifier: n
Classifier: /
Classifier: S
Classifier: t
Classifier: a
Classifier: b
Classifier: l
Classifier: e
